pyblish_nuke/__init__.py
pyblish_nuke/lib.py
pyblish_nuke/version.py
pyblish_nuke/nuke_path/menu.py
pyblish_nuke/plugins/__init__.py
pyblish_nuke/plugins/select_current_file.py
pyblish_nuke/plugins/select_host.py
pyblish_nuke/plugins/select_host_version.py
pyblish_nuke/vendor/Qt.py
pyblish_nuke/vendor/__init__.py
pyblish_nuke-2.1.2.dist-info/LICENSE.txt
pyblish_nuke-2.1.2.dist-info/METADATA
pyblish_nuke-2.1.2.dist-info/RECORD
pyblish_nuke-2.1.2.dist-info/WHEEL
pyblish_nuke-2.1.2.dist-info/top_level.txt
